day25/MOD-100_counter/design.v
// design code for mod-100 counter

module counter(
	input rst,clk,
	output [6:0]count);
reg [6:0]temp;
always @ (posedge clk)begin
	if(rst)
		temp<=0;
	else if(temp==99)
		temp<=0;
	else
		temp<=temp+1;
	end
assign count=temp;

endmodule

day25/MOD-100_counter/testbench.v
//test bench
`include"design.v"
module tb;
reg rst,clk;
wire [6:0]count;

counter dut(rst,clk,count);

always #5 clk=~clk;

initial begin
$monitor("Sim=%0t rst=%b counter=%d",$time,rst,count);
clk=0;
rst=1;
#13 rst=0;
#2000 $finish;
end
 
initial begin
$dumpfile("dump.vcd");
$dumpvars(0,tb);
end
endmodule

day25/MOD-100_counter/dump.vcd
$date
	Fri May  2 16:08:56 2025
$end
$version
	Icarus Verilog
$end
$timescale
	1s
$end
$scope module tb $end
$var wire 7 ! count [6:0] $end
$var reg 1 " clk $end
$var reg 1 # rst $end
$scope module dut $end
$var wire 1 " clk $end
$var wire 7 $ count [6:0] $end
$var wire 1 # rst $end
$var reg 7 % temp [6:0] $end
$upscope $end
$upscope $end
$enddefinitions $end
$comment Show the parameter values. $end
$dumpall
$end
#0
$dumpvars
bx %
bx $
1#
0"
bx !
$end
#5
b0 !
b0 $
b0 %
1"
#10
0"
#13
0#
#15
b1 !
b1 $
b1 %
1"
#20
0"
#25
b10 !
b10 $
b10 %
1"
#30
0"
#35
b11 !
b11 $
b11 %
1"
#40
0"
#45
b100 !
b100 $
b100 %
1"
#50
0"
#55
b101 !
b101 $
b101 %
1"
#60
0"
#65
b110 !
b110 $
b110 %
1"
#70
0"
#75
b111 !
b111 $
b111 %
1"
#80
0"
#85
b1000 !
b1000 $
b1000 %
1"
#90
0"
#95
b1001 !
b1001 $
b1001 %
1"
#100
0"
#105
b1010 !
b1010 $
b1010 %
1"
#110
0"
#115
b1011 !
b1011 $
b1011 %
1"
#120
0"
#125
b1100 !
b1100 $
b1100 %
1"
#130
0"
#135
b1101 !
b1101 $
b1101 %
1"
#140
0"
#145
b1110 !
b1110 $
b1110 %
1"
#150
0"
#155
b1111 !
b1111 $
b1111 %
1"
#160
0"
#165
b10000 !
b10000 $
b10000 %
1"
#170
0"
#175
b10001 !
b10001 $
b10001 %
1"
#180
0"
#185
b10010 !
b10010 $
b10010 %
1"
#190
0"
#195
b10011 !
b10011 $
b10011 %
1"
#200
0"
#205
b10100 !
b10100 $
b10100 %
1"
#210
0"
#215
b10101 !
b10101 $
b10101 %
1"
#220
0"
#225
b10110 !
b10110 $
b10110 %
1"
#230
0"
#235
b10111 !
b10111 $
b10111 %
1"
#240
0"
#245
b11000 !
b11000 $
b11000 %
1"
#250
0"
#255
b11001 !
b11001 $
b11001 %
1"
#260
0"
#265
b11010 !
b11010 $
b11010 %
1"
#270
0"
#275
b11011 !
b11011 $
b11011 %
1"
#280
0"
#285
b11100 !
b11100 $
b11100 %
1"
#290
0"
#295
b11101 !
b11101 $
b11101 %
1"
#300
0"
#305
b11110 !
b11110 $
b11110 %
1"
#310
0"
#315
b11111 !
b11111 $
b11111 %
1"
#320
0"
#325
b100000 !
b100000 $
b100000 %
1"
#330
0"
#335
b100001 !
b100001 $
b100001 %
1"
#340
0"
#345
b100010 !
b100010 $
b100010 %
1"
#350
0"
#355
b100011 !
b100011 $
b100011 %
1"
#360
0"
#365
b100100 !
b100100 $
b100100 %
1"
#370
0"
#375
b100101 !
b100101 $
b100101 %
1"
#380
0"
#385
b100110 !
b100110 $
b100110 %
1"
#390
0"
#395
b100111 !
b100111 $
b100111 %
1"
#400
0"
#405
b101000 !
b101000 $
b101000 %
1"
#410
0"
#415
b101001 !
b101001 $
b101001 %
1"
#420
0"
#425
b101010 !
b101010 $
b101010 %
1"
#430
0"
#435
b101011 !
b101011 $
b101011 %
1"
#440
0"
#445
b101100 !
b101100 $
b101100 %
1"
#450
0"
#455
b101101 !
b101101 $
b101101 %
1"
#460
0"
#465
b101110 !
b101110 $
b101110 %
1"
#470
0"
#475
b101111 !
b101111 $
b101111 %
1"
#480
0"
#485
b110000 !
b110000 $
b110000 %
1"
#490
0"
#495
b110001 !
b110001 $
b110001 %
1"
#500
0"
#505
b110010 !
b110010 $
b110010 %
1"
#510
0"
#515
b110011 !
b110011 $
b110011 %
1"
#520
0"
#525
b110100 !
b110100 $
b110100 %
1"
#530
0"
#535
b110101 !
b110101 $
b110101 %
1"
#540
0"
#545
b110110 !
b110110 $
b110110 %
1"
#550
0"
#555
b110111 !
b110111 $
b110111 %
1"
#560
0"
#565
b111000 !
b111000 $
b111000 %
1"
#570
0"
#575
b111001 !
b111001 $
b111001 %
1"
#580
0"
#585
b111010 !
b111010 $
b111010 %
1"
#590
0"
#595
b111011 !
b111011 $
b111011 %
1"
#600
0"
#605
b111100 !
b111100 $
b111100 %
1"
#610
0"
#615
b111101 !
b111101 $
b111101 %
1"
#620
0"
#625
b111110 !
b111110 $
b111110 %
1"
#630
0"
#635
b111111 !
b111111 $
b111111 %
1"
#640
0"
#645
b1000000 !
b1000000 $
b1000000 %
1"
#650
0"
#655
b1000001 !
b1000001 $
b1000001 %
1"
#660
0"
#665
b1000010 !
b1000010 $
b1000010 %
1"
#670
0"
#675
b1000011 !
b1000011 $
b1000011 %
1"
#680
0"
#685
b1000100 !
b1000100 $
b1000100 %
1"
#690
0"
#695
b1000101 !
b1000101 $
b1000101 %
1"
#700
0"
#705
b1000110 !
b1000110 $
b1000110 %
1"
#710
0"
#715
b1000111 !
b1000111 $
b1000111 %
1"
#720
0"
#725
b1001000 !
b1001000 $
b1001000 %
1"
#730
0"
#735
b1001001 !
b1001001 $
b1001001 %
1"
#740
0"
#745
b1001010 !
b1001010 $
b1001010 %
1"
#750
0"
#755
b1001011 !
b1001011 $
b1001011 %
1"
#760
0"
#765
b1001100 !
b1001100 $
b1001100 %
1"
#770
0"
#775
b1001101 !
b1001101 $
b1001101 %
1"
#780
0"
#785
b1001110 !
b1001110 $
b1001110 %
1"
#790
0"
#795
b1001111 !
b1001111 $
b1001111 %
1"
#800
0"
#805
b1010000 !
b1010000 $
b1010000 %
1"
#810
0"
#815
b1010001 !
b1010001 $
b1010001 %
1"
#820
0"
#825
b1010010 !
b1010010 $
b1010010 %
1"
#830
0"
#835
b1010011 !
b1010011 $
b1010011 %
1"
#840
0"
#845
b1010100 !
b1010100 $
b1010100 %
1"
#850
0"
#855
b1010101 !
b1010101 $
b1010101 %
1"
#860
0"
#865
b1010110 !
b1010110 $
b1010110 %
1"
#870
0"
#875
b1010111 !
b1010111 $
b1010111 %
1"
#880
0"
#885
b1011000 !
b1011000 $
b1011000 %
1"
#890
0"
#895
b1011001 !
b1011001 $
b1011001 %
1"
#900
0"
#905
b1011010 !
b1011010 $
b1011010 %
1"
#910
0"
#915
b1011011 !
b1011011 $
b1011011 %
1"
#920
0"
#925
b1011100 !
b1011100 $
b1011100 %
1"
#930
0"
#935
b1011101 !
b1011101 $
b1011101 %
1"
#940
0"
#945
b1011110 !
b1011110 $
b1011110 %
1"
#950
0"
#955
b1011111 !
b1011111 $
b1011111 %
1"
#960
0"
#965
b1100000 !
b1100000 $
b1100000 %
1"
#970
0"
#975
b1100001 !
b1100001 $
b1100001 %
1"
#980
0"
#985
b1100010 !
b1100010 $
b1100010 %
1"
#990
0"
#995
b1100011 !
b1100011 $
b1100011 %
1"
#1000
0"
#1005
b0 !
b0 $
b0 %
1"
#1010
0"
#1015
b1 !
b1 $
b1 %
1"
#1020
0"
#1025
b10 !
b10 $
b10 %
1"
#1030
0"
#1035
b11 !
b11 $
b11 %
1"
#1040
0"
#1045
b100 !
b100 $
b100 %
1"
#1050
0"
#1055
b101 !
b101 $
b101 %
1"
#1060
0"
#1065
b110 !
b110 $
b110 %
1"
#1070
0"
#1075
b111 !
b111 $
b111 %
1"
#1080
0"
#1085
b1000 !
b1000 $
b1000 %
1"
#1090
0"
#1095
b1001 !
b1001 $
b1001 %
1"
#1100
0"
#1105
b1010 !
b1010 $
b1010 %
1"
#1110
0"
#1115
b1011 !
b1011 $
b1011 %
1"
#1120
0"
#1125
b1100 !
b1100 $
b1100 %
1"
#1130
0"
#1135
b1101 !
b1101 $
b1101 %
1"
#1140
0"
#1145
b1110 !
b1110 $
b1110 %
1"
#1150
0"
#1155
b1111 !
b1111 $
b1111 %
1"
#1160
0"
#1165
b10000 !
b10000 $
b10000 %
1"
#1170
0"
#1175
b10001 !
b10001 $
b10001 %
1"
#1180
0"
#1185
b10010 !
b10010 $
b10010 %
1"
#1190
0"
#1195
b10011 !
b10011 $
b10011 %
1"
#1200
0"
#1205
b10100 !
b10100 $
b10100 %
1"
#1210
0"
#1215
b10101 !
b10101 $
b10101 %
1"
#1220
0"
#1225
b10110 !
b10110 $
b10110 %
1"
#1230
0"
#1235
b10111 !
b10111 $
b10111 %
1"
#1240
0"
#1245
b11000 !
b11000 $
b11000 %
1"
#1250
0"
#1255
b11001 !
b11001 $
b11001 %
1"
#1260
0"
#1265
b11010 !
b11010 $
b11010 %
1"
#1270
0"
#1275
b11011 !
b11011 $
b11011 %
1"
#1280
0"
#1285
b11100 !
b11100 $
b11100 %
1"
#1290
0"
#1295
b11101 !
b11101 $
b11101 %
1"
#1300
0"
#1305
b11110 !
b11110 $
b11110 %
1"
#1310
0"
#1315
b11111 !
b11111 $
b11111 %
1"
#1320
0"
#1325
b100000 !
b100000 $
b100000 %
1"
#1330
0"
#1335
b100001 !
b100001 $
b100001 %
1"
#1340
0"
#1345
b100010 !
b100010 $
b100010 %
1"
#1350
0"
#1355
b100011 !
b100011 $
b100011 %
1"
#1360
0"
#1365
b100100 !
b100100 $
b100100 %
1"
#1370
0"
#1375
b100101 !
b100101 $
b100101 %
1"
#1380
0"
#1385
b100110 !
b100110 $
b100110 %
1"
#1390
0"
#1395
b100111 !
b100111 $
b100111 %
1"
#1400
0"
#1405
b101000 !
b101000 $
b101000 %
1"
#1410
0"
#1415
b101001 !
b101001 $
b101001 %
1"
#1420
0"
#1425
b101010 !
b101010 $
b101010 %
1"
#1430
0"
#1435
b101011 !
b101011 $
b101011 %
1"
#1440
0"
#1445
b101100 !
b101100 $
b101100 %
1"
#1450
0"
#1455
b101101 !
b101101 $
b101101 %
1"
#1460
0"
#1465
b101110 !
b101110 $
b101110 %
1"
#1470
0"
#1475
b101111 !
b101111 $
b101111 %
1"
#1480
0"
#1485
b110000 !
b110000 $
b110000 %
1"
#1490
0"
#1495
b110001 !
b110001 $
b110001 %
1"
#1500
0"
#1505
b110010 !
b110010 $
b110010 %
1"
#1510
0"
#1515
b110011 !
b110011 $
b110011 %
1"
#1520
0"
#1525
b110100 !
b110100 $
b110100 %
1"
#1530
0"
#1535
b110101 !
b110101 $
b110101 %
1"
#1540
0"
#1545
b110110 !
b110110 $
b110110 %
1"
#1550
0"
#1555
b110111 !
b110111 $
b110111 %
1"
#1560
0"
#1565
b111000 !
b111000 $
b111000 %
1"
#1570
0"
#1575
b111001 !
b111001 $
b111001 %
1"
#1580
0"
#1585
b111010 !
b111010 $
b111010 %
1"
#1590
0"
#1595
b111011 !
b111011 $
b111011 %
1"
#1600
0"
#1605
b111100 !
b111100 $
b111100 %
1"
#1610
0"
#1615
b111101 !
b111101 $
b111101 %
1"
#1620
0"
#1625
b111110 !
b111110 $
b111110 %
1"
#1630
0"
#1635
b111111 !
b111111 $
b111111 %
1"
#1640
0"
#1645
b1000000 !
b1000000 $
b1000000 %
1"
#1650
0"
#1655
b1000001 !
b1000001 $
b1000001 %
1"
#1660
0"
#1665
b1000010 !
b1000010 $
b1000010 %
1"
#1670
0"
#1675
b1000011 !
b1000011 $
b1000011 %
1"
#1680
0"
#1685
b1000100 !
b1000100 $
b1000100 %
1"
#1690
0"
#1695
b1000101 !
b1000101 $
b1000101 %
1"
#1700
0"
#1705
b1000110 !
b1000110 $
b1000110 %
1"
#1710
0"
#1715
b1000111 !
b1000111 $
b1000111 %
1"
#1720
0"
#1725
b1001000 !
b1001000 $
b1001000 %
1"
#1730
0"
#1735
b1001001 !
b1001001 $
b1001001 %
1"
#1740
0"
#1745
b1001010 !
b1001010 $
b1001010 %
1"
#1750
0"
#1755
b1001011 !
b1001011 $
b1001011 %
1"
#1760
0"
#1765
b1001100 !
b1001100 $
b1001100 %
1"
#1770
0"
#1775
b1001101 !
b1001101 $
b1001101 %
1"
#1780
0"
#1785
b1001110 !
b1001110 $
b1001110 %
1"
#1790
0"
#1795
b1001111 !
b1001111 $
b1001111 %
1"
#1800
0"
#1805
b1010000 !
b1010000 $
b1010000 %
1"
#1810
0"
#1815
b1010001 !
b1010001 $
b1010001 %
1"
#1820
0"
#1825
b1010010 !
b1010010 $
b1010010 %
1"
#1830
0"
#1835
b1010011 !
b1010011 $
b1010011 %
1"
#1840
0"
#1845
b1010100 !
b1010100 $
b1010100 %
1"
#1850
0"
#1855
b1010101 !
b1010101 $
b1010101 %
1"
#1860
0"
#1865
b1010110 !
b1010110 $
b1010110 %
1"
#1870
0"
#1875
b1010111 !
b1010111 $
b1010111 %
1"
#1880
0"
#1885
b1011000 !
b1011000 $
b1011000 %
1"
#1890
0"
#1895
b1011001 !
b1011001 $
b1011001 %
1"
#1900
0"
#1905
b1011010 !
b1011010 $
b1011010 %
1"
#1910
0"
#1915
b1011011 !
b1011011 $
b1011011 %
1"
#1920
0"
#1925
b1011100 !
b1011100 $
b1011100 %
1"
#1930
0"
#1935
b1011101 !
b1011101 $
b1011101 %
1"
#1940
0"
#1945
b1011110 !
b1011110 $
b1011110 %
1"
#1950
0"
#1955
b1011111 !
b1011111 $
b1011111 %
1"
#1960
0"
#1965
b1100000 !
b1100000 $
b1100000 %
1"
#1970
0"
#1975
b1100001 !
b1100001 $
b1100001 %
1"
#1980
0"
#1985
b1100010 !
b1100010 $
b1100010 %
1"
#1990
0"
#1995
b1100011 !
b1100011 $
b1100011 %
1"
#2000
0"
#2005
b0 !
b0 $
b0 %
1"
