day1/det.v
module det_2(
input a,b,c,
output y0,y1);
assign y0= ~c;
assign y1= c;
endmodule

module det_2_tb;
reg a,b,c;
wire y0,y1;
det_2 dut (.*);
initial begin
$monitor("Time = %0t  a= %b b=%b c= %b y0 = %b y1 =%b  ",$time, a,b,c,y0,y1);
end
initial begin 
a= 0 ; b = 0 ; c=0 ;
 #10 a= 0 ; b = 0 ; c=0 ;
 #10 a= 0 ; b = 0 ; c=1 ;
 #10 a= 0 ; b = 1 ; c=0 ;
 #10 a= 0 ; b = 1 ; c=1 ;
 #10 a= 1 ; b = 0 ; c=0 ;
 #10 a= 1 ; b = 0 ; c=1 ;
 #10 a= 1 ; b = 1 ; c=0 ;
 #10 a= 1 ; b = 1 ; c=1 ;
 end
 
 initial begin
 $dumpfile ("det_2.vcd");
 $dumpvars (0, det_2_tb);
 end
 endmodule

day1/det_2.vcd
$date
	Wed Apr  9 12:51:22 2025
$end
$version
	Icarus Verilog
$end
$timescale
	1s
$end
$scope module det_2_tb $end
$var wire 1 ! y1 $end
$var wire 1 " y0 $end
$var reg 1 # a $end
$var reg 1 $ b $end
$var reg 1 % c $end
$scope module dut $end
$var wire 1 # a $end
$var wire 1 $ b $end
$var wire 1 % c $end
$var wire 1 " y0 $end
$var wire 1 ! y1 $end
$upscope $end
$upscope $end
$enddefinitions $end
$comment Show the parameter values. $end
$dumpall
$end
#0
$dumpvars
0%
0$
0#
1"
0!
$end
#20
0"
1!
1%
#30
1"
0!
0%
1$
#40
0"
1!
1%
#50
1"
0!
0%
0$
1#
#60
0"
1!
1%
#70
1"
0!
0%
1$
#80
0"
1!
1%
