day31/jk_latch/design.v
module jk_latch(
	input j,k,clk,rst,
	output q);
 reg temp;
 assign q=temp;
 always@(j,k,clk,rst)begin
 begin 
 	if(~rst)
 	temp<=0;
 	else 
 		if(clk)
 			case({j,k})
 			2'b00 : temp<=temp;
 			2'b01 : temp<=0;
 			2'b10 : temp<=1;
 			2'b11 : temp<=~temp;
 			endcase
 		else 
 		temp<=temp;
 	end
 	end
 endmodule

day31/jk_latch/testbench.v
`include"design.v"

 // testbench 
 
 module tb;
 reg j,k,clk,rst;
 wire q;
jk_latch dut(j,k,clk,rst,q);
always #5 clk = ~ clk;
initial begin
clk=0;
rst=0;  // asserting the reset 
#7 rst=1; // deasserting the reset 
{j,k}=0;
#10 {j,k}=1;
#7 {j,k}=2;
#8 {j,k}=3;
#9 {j,k}=2;
#2 rst=0;
#10 rst=1;
#2 {j,k}=3;
#10 $finish;
end
initial begin
$dumpfile("dump.vcd");
$dumpvars(0,tb);
end
endmodule

day31/jk_latch/dump.vcd
$date
	Tue May 13 10:52:09 2025
$end
$version
	Icarus Verilog
$end
$timescale
	1s
$end
$scope module tb $end
$var wire 1 ! q $end
$var reg 1 " clk $end
$var reg 1 # j $end
$var reg 1 $ k $end
$var reg 1 % rst $end
$scope module dut $end
$var wire 1 " clk $end
$var wire 1 # j $end
$var wire 1 $ k $end
$var wire 1 ! q $end
$var wire 1 % rst $end
$var reg 1 & temp $end
$upscope $end
$upscope $end
$enddefinitions $end
$comment Show the parameter values. $end
$dumpall
$end
#0
$dumpvars
0&
0%
x$
x#
0"
0!
$end
#5
1"
#7
0#
0$
1%
#10
0"
#15
1"
#17
1$
#20
0"
#24
1#
0$
#25
1!
1&
1"
#30
0"
#32
1$
#35
0!
0&
1"
#40
0"
#41
0$
#43
0%
#45
1"
#50
0"
#53
1%
#55
1!
1&
1$
1"
#60
0"
#65
0!
0&
1"
