day40/mealy_1100_overlapping/design.v
module mealy(
	input in_seq, clk, rst,
	output reg out);

reg [2:0] ps, ns;

parameter idle   = 3'b000;
parameter s1     = 3'b001;
parameter s11    = 3'b010;
parameter s110   = 3'b011;

always@(posedge clk)
	begin 
	if(!rst)
			ps<=idle;
		else 
			ps<=ns;
	end

always@(in_seq, ps)
begin 
case(ps)

idle :  if(in_seq)
		begin
		ns=s1;
		out=0;
		end
		
		else begin
		ns=idle;
		out=0;
		end
		
s1 :  if(in_seq)
		begin
		ns=s11;
		out=0;
		end
		
		else begin
		ns=idle;
		out=0;
		end

s11 :  if(in_seq)
		begin
		ns=s11;
		out=0;
		end
		
		else begin
		ns=s110;
		out=0;
		end
		
s110 :  if(in_seq)
		begin
		ns=s1;
		out=1;
		end
		
		else begin
		ns=idle;
		out=0;
		end	
endcase
end
endmodule

day40/mealy_1100_overlapping/testbench.v
`include"design.v"
module tb;
reg in_seq,clk,rst;
wire out;
mealy dut(.*);
initial begin
$monitor("time = %0t in_sequence = %b out = %b",$time,in_seq,out);
clk=0;
rst=0;
#13 rst=1;
in_seq=1;
#10 in_seq=1;
#10 in_seq=0;
#10 in_seq=0;
#20 $finish;
end
always #5 clk =~clk;
initial begin 
$dumpfile("dump.vcd");
$dumpvars(0,tb);
end
endmodule

day40/mealy_1100_overlapping/dump.vcd
$date
	Sat Jun  7 18:37:00 2025
$end
$version
	Icarus Verilog
$end
$timescale
	1s
$end
$scope module tb $end
$var wire 1 ! out $end
$var reg 1 " clk $end
$var reg 1 # in_seq $end
$var reg 1 $ rst $end
$scope module dut $end
$var wire 1 " clk $end
$var wire 1 # in_seq $end
$var wire 1 $ rst $end
$var parameter 3 % idle $end
$var parameter 3 & s1 $end
$var parameter 3 ' s11 $end
$var parameter 3 ( s110 $end
$var reg 3 ) ns [2:0] $end
$var reg 1 ! out $end
$var reg 3 * ps [2:0] $end
$upscope $end
$upscope $end
$enddefinitions $end
$comment Show the parameter values. $end
$dumpall
b11 (
b10 '
b1 &
b0 %
$end
#0
$dumpvars
bx *
bx )
0$
x#
0"
x!
$end
#5
0!
b0 )
b0 *
1"
#10
0"
#13
b1 )
1#
1$
#15
b10 )
b1 *
1"
#20
0"
#25
b10 *
1"
#30
0"
#33
b11 )
0#
#35
b0 )
b11 *
1"
#40
0"
#45
b0 *
1"
