hls_assignment/comparator/comparator.v
// Name : Munees Sanid
// Roll No: KVLSI2501076
// Question No:A

module comparator(
	input [3:0]a,
	input [3:0]b,
	output a_gt_b,
	output a_eq_b,
	output a_ls_b);
wire w0,w1,w2,w3,w4,w5,w6,w7,w8,w9,w10,w11;
wire l1,l2,l3,l4,l5,l6,l7,l8;
// xnor operation 
xnor x1(w4,a[3],b[3]);
xnor x2(w5,a[2],b[2]);
xnor x3(w6,a[1],b[1]);
xnor x4(w7,a[0],b[0]);

// not operation of b
not n1 (w0,b[3]);
not n2 (w1,b[2]);
not n3 (w2,b[1]);
not n4 (w3,b[0]);

// not operation of a 
not n5 (l5,a[3]);
not n6 (l6,a[2]);
not n7 (l7,a[1]);
not n8 (l8,a[0]);
// a greater tha b
and a1(w8,a[3],w0);
and a2(w9,a[2],w1,w4);
and a3(w10,a[1],w2,w4,w5);
and a4(w11,a[0],w3,w4,w5,w6);
or o1(a_gt_b,w8,w9,w10,w11);

// a == b operation
and a5(a_eq_b,w4,w5,w6,w7);

// a lesser than b operation 
and a6(l1,b[3],l5);
and a7(l2,b[2],l6,w4);
and a8(l3,b[1],l7,w4,w5);
and a9(l4,b[0],l8,w4,w5,w6);
or o2(a_ls_b,l1,l2,l3,l4);
endmodule

hls_assignment/comparator/comparator_tb.v
`include "comparator.v"

module comparator_tb;
reg [3:0] a, b;
wire a_gt_b, a_eq_b, a_ls_b;

comparator dut (.*); // It automatically port the connection 

// To display the value
initial begin
$monitor("Time = %0t  a = %b  b = %b   ::   a_gt_b = %b a_eq_b = %b  a_ls_b = %b",$time, a, b, a_gt_b, a_eq_b, a_ls_b);
end
// few combination of 4 bit a and b 
initial begin
 a = 4'b0000; b = 4'b0000;
 #10 a = 4'b0001; b = 4'b0000;
 #10 a = 4'b0010; b = 4'b0011;
 #10 a = 4'b0101; b = 4'b0101;
 #10 a = 4'b0111; b = 4'b0110;
 #10 a = 4'b1000; b = 4'b1000;
 #10 a = 4'b1100; b = 4'b1101;
 #10 a = 4'b1111; b = 4'b0001;
 #10 a = 4'b0000; b = 4'b1111;
end

initial begin
 $dumpfile("dump.vcd");
 $dumpvars(0, comparator_tb);
end
endmodule

hls_assignment/comparator/dump.vcd
$date
	Mon Apr 14 13:14:31 2025
$end
$version
	Icarus Verilog
$end
$timescale
	1s
$end
$scope module comparator_tb $end
$var wire 1 ! a_ls_b $end
$var wire 1 " a_gt_b $end
$var wire 1 # a_eq_b $end
$var reg 4 $ a [3:0] $end
$var reg 4 % b [3:0] $end
$scope module dut $end
$var wire 4 & a [3:0] $end
$var wire 1 # a_eq_b $end
$var wire 1 " a_gt_b $end
$var wire 1 ! a_ls_b $end
$var wire 4 ' b [3:0] $end
$var wire 1 ( l1 $end
$var wire 1 ) l2 $end
$var wire 1 * l3 $end
$var wire 1 + l4 $end
$var wire 1 , l5 $end
$var wire 1 - l6 $end
$var wire 1 . l7 $end
$var wire 1 / l8 $end
$var wire 1 0 w0 $end
$var wire 1 1 w1 $end
$var wire 1 2 w10 $end
$var wire 1 3 w11 $end
$var wire 1 4 w2 $end
$var wire 1 5 w3 $end
$var wire 1 6 w4 $end
$var wire 1 7 w5 $end
$var wire 1 8 w6 $end
$var wire 1 9 w7 $end
$var wire 1 : w8 $end
$var wire 1 ; w9 $end
$upscope $end
$upscope $end
$enddefinitions $end
$comment Show the parameter values. $end
$dumpall
$end
#0
$dumpvars
0;
0:
19
18
17
16
15
14
03
02
11
10
1/
1.
1-
1,
0+
0*
0)
0(
b0 '
b0 &
b0 %
b0 $
1#
0"
0!
$end
#10
1"
0#
13
09
0/
b1 $
b1 &
#20
0"
1!
1+
03
04
05
0.
1/
02
b11 %
b11 '
b10 $
b10 &
#30
0!
0+
1#
0"
01
14
19
0-
1.
0/
0;
b101 %
b101 '
b101 $
b101 &
#40
13
0#
1"
09
04
15
0.
02
b110 %
b110 '
b111 $
b111 &
#50
0"
1#
03
00
11
14
19
0,
1-
1.
1/
0:
b1000 %
b1000 '
b1000 $
b1000 &
#60
1!
0#
1+
0"
09
01
05
0-
0;
b1101 %
b1101 '
b1100 $
b1100 &
#70
0!
0+
1:
1"
06
07
10
11
08
19
0.
0/
02
b1 %
b1 '
b1111 $
b1111 &
#80
1!
0"
00
01
04
1(
09
1,
1-
1.
1/
0:
b1111 %
b1111 '
b0 $
b0 &
