day31/moore_101_overlapping/design.v
// design code for 101 moore overlapping

module mealy(
	input in_seq,clk,rst,
	output reg out);
// declaration of state variable
reg [1:0] ps,ns;
// state encoding
parameter idle=2'b00;
parameter s1=2'b01;
parameter s2=2'b10;
parameter s3=2'b11;

// implement the state registor
always@(posedge clk)
begin 
	if(~rst)
		ps<=idle;
	else
		ps<=ns;
end
// always block for nsd and od

always @(in_seq,ps)begin
case(ps)
idle:if(in_seq)begin
	ns=s1;
	out=0;
	end
	else begin
	ns=idle;
	out=0;
	end
s1:if(in_seq)begin
	ns=s1;
	out=0;
	end
	else begin
	ns=s2;
	out=0;
	end
s2:if(in_seq)begin
	ns=s1;
	out=1;
	end
	else begin
	ns=idle;
	out=0;
	end
s3:if(in_seq)begin
	ns=s1;
	out=1;
	end
	else begin
	ns=s2;
	out=0;
	end
endcase
end
endmodule

day31/fsm_mealy_101_overlapping/testbench.v
`include"design.v"
// test bench
module tb;
reg in_seq,clk,rst;
wire out;
mealy dut(.*);
initial begin
$monitor("time = %0t in_sequence = %b out = %b",$time,in_seq,out);
clk=0;
rst=0;
#12 rst=1;
in_seq=1;
#10 in_seq=0;
#10 in_seq=1;
#10 in_seq=0;
#10 in_seq=1;
#10 in_seq=0;
#10 in_seq=1;
#20 $finish;
end
always #5 clk =~clk;
initial begin 
$dumpfile("dump.vcd");
$dumpvars(0,tb);
end
endmodule

day31/fsm_mealy_101_overlapping/dump.vcd
$date
	Tue May 13 12:41:03 2025
$end
$version
	Icarus Verilog
$end
$timescale
	1s
$end
$scope module tb $end
$var wire 1 ! out $end
$var reg 1 " clk $end
$var reg 1 # in_seq $end
$var reg 1 $ rst $end
$scope module dut $end
$var wire 1 " clk $end
$var wire 1 # in_seq $end
$var wire 1 $ rst $end
$var parameter 2 % idle $end
$var parameter 2 & s1 $end
$var parameter 2 ' s2 $end
$var reg 2 ( ns [1:0] $end
$var reg 1 ! out $end
$var reg 2 ) ps [1:0] $end
$upscope $end
$upscope $end
$enddefinitions $end
$comment Show the parameter values. $end
$dumpall
b10 '
b1 &
b0 %
$end
#0
$dumpvars
bx )
bx (
0$
x#
0"
x!
$end
#5
0!
b0 (
b0 )
1"
#10
0"
#12
b1 (
1#
1$
#15
b1 )
1"
#20
0"
#22
b10 (
0#
#25
b0 (
b10 )
1"
#30
0"
#32
1!
b1 (
1#
#35
0!
b1 )
1"
#40
0"
#42
b10 (
0#
#45
b0 (
b10 )
1"
#50
0"
#52
1!
b1 (
1#
#55
0!
b1 )
1"
#60
0"
#62
b10 (
0#
#65
b0 (
b10 )
1"
#70
0"
#72
1!
b1 (
1#
#75
0!
b1 )
1"
