day20/LFSR/clock.v
`timescale 1ns/1ps
module clock(output reg clk);
    real freq = 500; // 500 MHZ , average clock speed of fpga 
    real time_period, ton; 
    real duty = 50; 

    initial begin
        clk = 0;
        time_period = (1000 / freq);
        ton = (time_period * duty) / 100;
        #512 $finish; // 2^8 =256 , controlling lfsr over clock
    end

    always begin
        # (time_period - ton) clk = 1;
        # ton clk = 0;
    end
endmodule

day20/LFSR/dff.v
// design code for d flip flop without reset
module dff (
    input d, 
    input clk, 
    output reg q
);

    always @(posedge clk) begin
        q <= d;
    end

endmodule

day20/LFSR/lfsr.v
`include"dff.v"
module lfsr(
	input clk,
	output wire [7:0]q);
wire y,y1,y2;
dff f1(y,clk,q[0]);
dff f2(q[0],clk,q[1]);
dff f3(q[1],clk,q[2]);
dff f4(q[2],clk,q[3]);
dff f5(q[3],clk,q[4]);
dff f6(q[4],clk,q[5]);
dff f7(q[5],clk,q[6]);
dff f8(q[6],clk,q[7]);
assign y1 = q[6]^q[7];
assign y2 = q[4]^q[5];
assign y= y1^y2;
endmodule

day20/LFSR/lfsr_tb.v
`include"clock.v"
`include"lfsr.v"
module tb;
wire clk;
wire [7:0]q;
integer t_count=0;
reg [7:0] q1=0;
initial begin
    force tb.dut.q = 4'b0001; 
    #5 release tb.dut.q;       
end
lfsr dut(clk,q);
clock c1(clk);

always @(posedge clk) begin
if (q != q1) begin
t_count = t_count + 1;
q1 = q;
 end
 end
initial begin 
$monitor("%d :: q = %b",t_count,q);
end
initial begin 
$dumpfile("dump.vcd");
$dumpvars(0,tb);
end
endmodule

day20/LFSR/dump.vcd
$date
	Sat Apr 26 18:49:00 2025
$end
$version
	Icarus Verilog
$end
$timescale
	1ps
$end
$scope module tb $end
$var wire 8 ! q [7:0] $end
$var wire 1 " clk $end
$var reg 8 # q1 [7:0] $end
$var integer 32 $ t_count [31:0] $end
$scope module c1 $end
$var reg 1 " clk $end
$var real 1 % duty $end
$var real 1 & freq $end
$var real 1 ' time_period $end
$var real 1 ( ton $end
$upscope $end
$scope module dut $end
$var wire 1 " clk $end
$var wire 1 ) y $end
$var wire 1 * y1 $end
$var wire 1 + y2 $end
$var wire 8 , q [7:0] $end
$scope module f1 $end
$var wire 1 " clk $end
$var wire 1 ) d $end
$var reg 1 - q $end
$upscope $end
$scope module f2 $end
$var wire 1 " clk $end
$var wire 1 . d $end
$var reg 1 / q $end
$upscope $end
$scope module f3 $end
$var wire 1 " clk $end
$var wire 1 0 d $end
$var reg 1 1 q $end
$upscope $end
$scope module f4 $end
$var wire 1 " clk $end
$var wire 1 2 d $end
$var reg 1 3 q $end
$upscope $end
$scope module f5 $end
$var wire 1 " clk $end
$var wire 1 4 d $end
$var reg 1 5 q $end
$upscope $end
$scope module f6 $end
$var wire 1 " clk $end
$var wire 1 6 d $end
$var reg 1 7 q $end
$upscope $end
$scope module f7 $end
$var wire 1 " clk $end
$var wire 1 8 d $end
$var reg 1 9 q $end
$upscope $end
$scope module f8 $end
$var wire 1 " clk $end
$var wire 1 : d $end
$var reg 1 ; q $end
$upscope $end
$upscope $end
$upscope $end
$enddefinitions $end
$comment Show the parameter values. $end
$dumpall
$end
#0
$dumpvars
x;
0:
x9
08
x7
06
x5
04
x3
02
x1
00
x/
1.
x-
b1 ,
0+
0*
0)
r1 (
r2 '
r500 &
r50 %
b0 $
b0 #
0"
b1 !
$end
#1000
0-
1/
01
03
05
07
09
b1 !
b1 ,
0;
b1 #
b1 $
1"
#2000
0"
#3000
1"
#4000
0"
#5000
12
0/
11
b10 #
b10 $
00
0.
1"
b100 !
b100 ,
#6000
0"
#7000
14
02
13
b1000 !
b1000 ,
01
b100 #
b11 $
1"
#8000
0"
#9000
1)
1+
04
16
03
b10000 !
b10000 ,
15
b1000 #
b100 $
1"
#10000
0"
#11000
18
06
1.
17
05
b100001 !
b100001 ,
1-
b10000 #
b101 $
1"
#12000
0"
#13000
0+
1*
10
08
1:
1/
07
b1000011 !
b1000011 ,
19
b100001 #
b110 $
1"
#14000
0"
#15000
0:
12
1;
09
b10000111 !
b10000111 ,
11
b1000011 #
b111 $
1"
#16000
0"
#17000
0)
0*
14
13
b1111 !
b1111 ,
0;
b10000111 #
b1000 $
1"
#18000
0"
#19000
1)
1+
16
0.
15
b11110 !
b11110 ,
0-
b1111 #
b1001 $
1"
#20000
0"
#21000
0)
0+
1.
00
18
1-
0/
b111101 !
b111101 ,
17
b11110 #
b1010 $
1"
#22000
0"
#23000
1)
1*
1:
02
10
0.
19
01
1/
b1111010 !
b1111010 ,
0-
b111101 #
b1011 $
1"
#24000
0"
#25000
0)
0*
1.
00
12
04
1-
0/
11
03
b11110101 !
b11110101 ,
1;
b1111010 #
b1100 $
1"
#26000
0"
#27000
1)
1+
06
14
02
10
0.
05
13
01
1/
b11101010 !
b11101010 ,
0-
b11110101 #
b1101 $
1"
#28000
0"
#29000
1.
00
12
04
16
08
1-
0/
11
03
15
b11010101 !
b11010101 ,
07
b11101010 #
b1110 $
1"
#30000
0"
#31000
0)
1*
0:
18
06
14
02
10
09
17
05
13
01
b10101011 !
b10101011 ,
1/
b11010101 #
b1111 $
1"
#32000
0"
#33000
0.
12
04
16
08
1:
0-
11
03
15
07
19
b1010110 !
b1010110 ,
0;
b10101011 #
b10000 $
1"
#34000
0"
#35000
0:
18
06
14
00
1;
09
17
05
13
b10101100 !
b10101100 ,
0/
b1010110 #
b10001 $
1"
#36000
0"
#37000
02
16
08
1:
01
15
07
19
b1011000 !
b1011000 ,
0;
b10101100 #
b10010 $
1"
#38000
0"
#39000
1)
0+
0:
18
04
1;
09
17
b10110000 !
b10110000 ,
03
b1011000 #
b10011 $
1"
#40000
0"
#41000
0)
1+
1.
06
1:
1-
05
19
b1100001 !
b1100001 ,
0;
b10110000 #
b10100 $
1"
#42000
0"
#43000
0*
0+
08
10
0.
1;
07
1/
b11000010 !
b11000010 ,
0-
b1100001 #
b10101 $
1"
#44000
0"
#45000
1)
1*
00
12
0:
0/
11
b10000100 !
b10000100 ,
09
b11000010 #
b10110 $
1"
#46000
0"
#47000
0)
0*
14
02
1.
0;
13
01
b1001 !
b1001 ,
1-
b10000100 #
b10111 $
1"
#48000
0"
#49000
1)
1+
0.
10
04
16
0-
1/
03
b10010 !
b10010 ,
15
b1001 #
b11000 $
1"
#50000
0"
#51000
18
06
12
00
1.
17
05
11
0/
b100101 !
b100101 ,
1-
b10010 #
b11001 $
1"
#52000
0"
#53000
0+
1*
10
02
14
08
1:
1/
01
13
07
b1001011 !
b1001011 ,
19
b100101 #
b11010 $
1"
#54000
0"
#55000
0)
1+
0:
16
04
12
1;
09
15
03
b10010111 !
b10010111 ,
11
b1001011 #
b11011 $
1"
#56000
0"
#57000
1)
0*
0.
14
06
18
0-
13
05
17
b101110 !
b101110 ,
0;
b10010111 #
b11100 $
1"
#58000
0"
#59000
0)
1*
1:
08
16
00
1.
19
07
15
0/
b1011101 !
b1011101 ,
1-
b101110 #
b11101 $
1"
#60000
0"
#61000
1)
0+
0.
10
02
18
0:
0-
1/
01
17
09
b10111010 !
b10111010 ,
1;
b1011101 #
b11110 $
1"
#62000
0"
#63000
1:
04
12
00
1.
0;
19
03
11
0/
b1110101 !
b1110101 ,
1-
b10111010 #
b11111 $
1"
#64000
0"
#65000
1+
0*
10
02
14
06
1/
01
13
05
b11101011 !
b11101011 ,
1;
b1110101 #
b100000 $
1"
#66000
0"
#67000
08
16
04
12
07
15
03
b11010111 !
b11010111 ,
11
b11101011 #
b100001 $
1"
#68000
0"
#69000
0)
1*
14
06
18
0:
13
05
17
b10101111 !
b10101111 ,
09
b11010111 #
b100010 $
1"
#70000
0"
#71000
1:
08
16
0.
0;
19
07
15
b1011110 !
b1011110 ,
0-
b10101111 #
b100011 $
1"
#72000
0"
#73000
1)
0+
00
18
0:
0/
17
09
b10111100 !
b10111100 ,
1;
b1011110 #
b100100 $
1"
#74000
0"
#75000
1:
02
1.
0;
19
01
b1111001 !
b1111001 ,
1-
b10111100 #
b100101 $
1"
#76000
0"
#77000
0)
0*
10
04
1/
03
b11110011 !
b11110011 ,
1;
b1111001 #
b100110 $
1"
#78000
0"
#79000
1)
1+
06
12
0.
05
11
b11100110 !
b11100110 ,
0-
b11110011 #
b100111 $
1"
#80000
0"
#81000
0)
0+
1.
00
14
08
1-
0/
13
b11001101 !
b11001101 ,
07
b11100110 #
b101000 $
1"
#82000
0"
#83000
1*
1+
0:
16
02
10
0.
09
15
01
1/
b10011010 !
b10011010 ,
0-
b11001101 #
b101001 $
1"
#84000
0"
#85000
0+
0*
00
12
04
18
0/
11
03
17
b110100 !
b110100 ,
0;
b10011010 #
b101010 $
1"
#86000
0"
#87000
1*
1+
1:
06
14
02
19
05
13
b1101000 !
b1101000 ,
01
b110100 #
b101011 $
1"
#88000
0"
#89000
1)
0*
04
16
08
03
15
07
b11010000 !
b11010000 ,
1;
b1101000 #
b101100 $
1"
#90000
0"
#91000
0)
1*
0:
18
06
1.
09
17
05
b10100001 !
b10100001 ,
1-
b11010000 #
b101101 $
1"
#92000
0"
#93000
1)
0+
0.
10
08
1:
0-
1/
07
19
b1000010 !
b1000010 ,
0;
b10100001 #
b101110 $
1"
#94000
0"
#95000
0:
12
00
1.
1;
09
11
0/
b10000101 !
b10000101 ,
1-
b1000010 #
b101111 $
1"
#96000
0"
#97000
0)
0*
10
02
14
1/
01
13
b1011 !
b1011 ,
0;
b10000101 #
b110000 $
1"
#98000
0"
#99000
1)
1+
16
04
12
0.
15
03
11
b10110 !
b10110 ,
0-
b1011 #
b110001 $
1"
#100000
0"
#101000
1.
00
14
06
18
1-
0/
13
05
b101101 !
b101101 ,
17
b10110 #
b110010 $
1"
#102000
0"
#103000
0)
1*
1:
08
16
02
10
19
07
15
01
b1011011 !
b1011011 ,
1/
b101101 #
b110011 $
1"
#104000
0"
#105000
1)
0+
0.
12
04
18
0:
0-
11
03
17
09
b10110110 !
b10110110 ,
1;
b1011011 #
b110100 $
1"
#106000
0"
#107000
0)
1+
1:
06
14
00
1.
0;
19
05
13
0/
b1101101 !
b1101101 ,
1-
b10110110 #
b110101 $
1"
#108000
0"
#109000
1)
0*
0.
10
02
16
08
0-
1/
01
15
07
b11011010 !
b11011010 ,
1;
b1101101 #
b110110 $
1"
#110000
0"
#111000
1*
0+
0:
18
04
12
00
1.
09
17
03
11
0/
b10110101 !
b10110101 ,
1-
b11011010 #
b110111 $
1"
#112000
0"
#113000
0)
1+
10
02
14
06
1:
1/
01
13
05
19
b1101011 !
b1101011 ,
0;
b10110101 #
b111000 $
1"
#114000
0"
#115000
1)
0*
08
16
04
12
0.
1;
07
15
03
11
b11010110 !
b11010110 ,
0-
b1101011 #
b111001 $
1"
#116000
0"
#117000
0)
1*
1.
00
14
06
18
0:
1-
0/
13
05
17
b10101101 !
b10101101 ,
09
b11010110 #
b111010 $
1"
#118000
0"
#119000
1:
08
16
02
10
0.
0;
19
07
15
01
1/
b1011010 !
b1011010 ,
0-
b10101101 #
b111011 $
1"
#120000
0"
#121000
1)
0+
00
12
04
18
0:
0/
11
03
17
09
b10110100 !
b10110100 ,
1;
b1011010 #
b111100 $
1"
#122000
0"
#123000
0)
1+
1:
06
14
02
1.
0;
19
05
13
01
b1101001 !
b1101001 ,
1-
b10110100 #
b111101 $
1"
#124000
0"
#125000
1)
0*
0.
10
04
16
08
0-
1/
03
15
07
b11010010 !
b11010010 ,
1;
b1101001 #
b111110 $
1"
#126000
0"
#127000
0)
1*
0:
18
06
12
00
1.
09
17
05
11
0/
b10100101 !
b10100101 ,
1-
b11010010 #
b111111 $
1"
#128000
0"
#129000
1)
0+
0.
10
02
14
08
1:
0-
1/
01
13
07
19
b1001010 !
b1001010 ,
0;
b10100101 #
b1000000 $
1"
#130000
0"
#131000
0)
1+
0:
16
04
12
00
1.
1;
09
15
03
11
0/
b10010101 !
b10010101 ,
1-
b1001010 #
b1000001 $
1"
#132000
0"
#133000
1)
0*
0.
10
02
14
06
18
0-
1/
01
13
05
17
b101010 !
b101010 ,
0;
b10010101 #
b1000010 $
1"
#134000
0"
#135000
0)
1*
1:
08
16
04
12
00
1.
19
07
15
03
11
0/
b1010101 !
b1010101 ,
1-
b101010 #
b1000011 $
1"
#136000
0"
#137000
0.
10
02
14
06
18
0:
0-
1/
01
13
05
17
09
b10101010 !
b10101010 ,
1;
b1010101 #
b1000100 $
1"
#138000
0"
#139000
1:
08
16
04
12
00
0;
19
07
15
03
11
b1010100 !
b1010100 ,
0/
b10101010 #
b1000101 $
1"
#140000
0"
#141000
02
14
06
18
0:
01
13
05
17
09
b10101000 !
b10101000 ,
1;
b1010100 #
b1000110 $
1"
#142000
0"
#143000
1:
08
16
04
0;
19
07
15
b1010000 !
b1010000 ,
03
b10101000 #
b1000111 $
1"
#144000
0"
#145000
06
18
0:
05
17
09
b10100000 !
b10100000 ,
1;
b1010000 #
b1001000 $
1"
#146000
0"
#147000
1)
0+
1:
08
0;
19
b1000000 !
b1000000 ,
07
b10100000 #
b1001001 $
1"
#148000
0"
#149000
1.
0:
1-
09
b10000001 !
b10000001 ,
1;
b1000000 #
b1001010 $
1"
#150000
0"
#151000
0)
0*
10
0;
b11 !
b11 ,
1/
b10000001 #
b1001011 $
1"
#152000
0"
#153000
0.
12
0-
b110 !
b110 ,
11
b11 #
b1001100 $
1"
#154000
0"
#155000
14
00
13
b1100 !
b1100 ,
0/
b110 #
b1001101 $
1"
#156000
0"
#157000
1)
1+
02
16
01
b11000 !
b11000 ,
15
b1100 #
b1001110 $
1"
#158000
0"
#159000
0)
0+
18
04
1.
17
03
b110001 !
b110001 ,
1-
b11000 #
b1001111 $
1"
#160000
0"
#161000
1+
1*
0.
10
06
1:
0-
1/
05
b1100010 !
b1100010 ,
19
b110001 #
b1010000 $
1"
#162000
0"
#163000
0*
0+
08
12
00
1;
07
11
b11000100 !
b11000100 ,
0/
b1100010 #
b1010001 $
1"
#164000
0"
#165000
1)
1*
02
14
0:
01
13
b10001000 !
b10001000 ,
09
b11000100 #
b1010010 $
1"
#166000
0"
#167000
0*
1+
16
04
1.
0;
15
03
b10001 !
b10001 ,
1-
b10001000 #
b1010011 $
1"
#168000
0"
#169000
10
06
18
1/
05
b100011 !
b100011 ,
17
b10001 #
b1010100 $
1"
#170000
0"
#171000
1*
0+
1:
08
12
19
07
b1000111 !
b1000111 ,
11
b100011 #
b1010101 $
1"
#172000
0"
#173000
14
0:
13
09
b10001111 !
b10001111 ,
1;
b1000111 #
b1010110 $
1"
#174000
0"
#175000
0*
1+
16
0;
b11111 !
b11111 ,
15
b10001111 #
b1010111 $
1"
#176000
0"
#177000
0)
0+
18
b111111 !
b111111 ,
17
b11111 #
b1011000 $
1"
#178000
0"
#179000
1)
1*
1:
0.
19
b1111110 !
b1111110 ,
0-
b111111 #
b1011001 $
1"
#180000
0"
#181000
0)
0*
1.
00
1-
0/
b11111101 !
b11111101 ,
1;
b1111110 #
b1011010 $
1"
#182000
0"
#183000
02
10
0.
01
1/
b11111010 !
b11111010 ,
0-
b11111101 #
b1011011 $
1"
#184000
0"
#185000
00
12
04
0/
11
b11110100 !
b11110100 ,
03
b11111010 #
b1011100 $
1"
#186000
0"
#187000
1)
1+
06
14
02
05
13
b11101000 !
b11101000 ,
01
b11110100 #
b1011101 $
1"
#188000
0"
#189000
1.
04
16
08
1-
03
15
b11010001 !
b11010001 ,
07
b11101000 #
b1011110 $
1"
#190000
0"
#191000
0)
1*
0:
18
06
10
09
17
05
b10100011 !
b10100011 ,
1/
b11010001 #
b1011111 $
1"
#192000
0"
#193000
1)
0+
0.
12
08
1:
0-
11
07
19
b1000110 !
b1000110 ,
0;
b10100011 #
b1100000 $
1"
#194000
0"
#195000
0:
14
00
1.
1;
09
13
0/
b10001101 !
b10001101 ,
1-
b1000110 #
b1100001 $
1"
#196000
0"
#197000
1+
0*
10
02
16
1/
01
15
b11011 !
b11011 ,
0;
b10001101 #
b1100010 $
1"
#198000
0"
#199000
0)
0+
18
04
12
17
03
b110111 !
b110111 ,
11
b11011 #
b1100011 $
1"
#200000
0"
#201000
1+
1*
0.
14
06
1:
0-
13
05
b1101110 !
b1101110 ,
19
b110111 #
b1100100 $
1"
#202000
0"
#203000
1)
0*
08
16
00
1;
07
15
b11011100 !
b11011100 ,
0/
b1101110 #
b1100101 $
1"
#204000
0"
#205000
0+
1*
1.
02
18
0:
1-
01
17
b10111001 !
b10111001 ,
09
b11011100 #
b1100110 $
1"
#206000
0"
#207000
1:
04
10
0;
19
03
b1110011 !
b1110011 ,
1/
b10111001 #
b1100111 $
1"
#208000
0"
#209000
1+
0*
12
06
11
05
b11100111 !
b11100111 ,
1;
b1110011 #
b1101000 $
1"
#210000
0"
#211000
0)
0+
08
14
07
b11001111 !
b11001111 ,
13
b11100111 #
b1101001 $
1"
#212000
0"
#213000
1+
1*
0.
16
0:
0-
15
b10011110 !
b10011110 ,
09
b11001111 #
b1101010 $
1"
#214000
0"
#215000
0*
0+
18
00
0;
17
b111100 !
b111100 ,
0/
b10011110 #
b1101011 $
1"
#216000
0"
#217000
1)
1*
02
1:
01
b1111000 !
b1111000 ,
19
b111100 #
b1101100 $
1"
#218000
0"
#219000
0)
0*
04
1.
1;
03
b11110001 !
b11110001 ,
1-
b1111000 #
b1101101 $
1"
#220000
0"
#221000
1)
1+
0.
10
06
0-
1/
b11100010 !
b11100010 ,
05
b11110001 #
b1101110 $
1"
#222000
0"
#223000
0)
0+
08
12
00
1.
07
11
0/
b11000101 !
b11000101 ,
1-
b11100010 #
b1101111 $
1"
#224000
0"
#225000
1)
1*
0.
10
02
14
0:
0-
1/
01
13
b10001010 !
b10001010 ,
09
b11000101 #
b1110000 $
1"
#226000
0"
#227000
0*
1+
16
04
12
00
1.
0;
15
03
11
0/
b10101 !
b10101 ,
1-
b10001010 #
b1110001 $
1"
#228000
0"
#229000
10
02
14
06
18
1/
01
13
05
b101011 !
b101011 ,
17
b10101 #
b1110010 $
1"
#230000
0"
#231000
0)
1*
1:
08
16
04
12
19
07
15
03
b1010111 !
b1010111 ,
11
b101011 #
b1110011 $
1"
#232000
0"
#233000
0.
14
06
18
0:
0-
13
05
17
09
b10101110 !
b10101110 ,
1;
b1010111 #
b1110100 $
1"
#234000
0"
#235000
1:
08
16
00
0;
19
07
15
b1011100 !
b1011100 ,
0/
b10101110 #
b1110101 $
1"
#236000
0"
#237000
1)
0+
02
18
0:
01
17
09
b10111000 !
b10111000 ,
1;
b1011100 #
b1110110 $
1"
#238000
0"
#239000
1:
04
1.
0;
19
03
b1110001 !
b1110001 ,
1-
b10111000 #
b1110111 $
1"
#240000
0"
#241000
1+
0*
10
06
1/
05
b11100011 !
b11100011 ,
1;
b1110001 #
b1111000 $
1"
#242000
0"
#243000
0)
0+
08
12
07
b11000111 !
b11000111 ,
11
b11100011 #
b1111001 $
1"
#244000
0"
#245000
1)
1*
0.
14
0:
0-
13
b10001110 !
b10001110 ,
09
b11000111 #
b1111010 $
1"
#246000
0"
#247000
0*
1+
16
00
1.
0;
15
0/
b11101 !
b11101 ,
1-
b10001110 #
b1111011 $
1"
#248000
0"
#249000
0)
0+
10
02
18
1/
01
b111011 !
b111011 ,
17
b11101 #
b1111100 $
1"
#250000
0"
#251000
1)
1*
1:
04
12
0.
19
03
11
b1110110 !
b1110110 ,
0-
b111011 #
b1111101 $
1"
#252000
0"
#253000
1+
0*
1.
00
14
06
1-
0/
13
05
b11101101 !
b11101101 ,
1;
b1110110 #
b1111110 $
1"
#254000
0"
#255000
08
16
02
10
07
15
01
b11011011 !
b11011011 ,
1/
b11101101 #
b1111111 $
1"
#256000
0"
#257000
0+
1*
12
04
18
0:
11
03
17
b10110111 !
b10110111 ,
09
b11011011 #
b10000000 $
1"
#258000
0"
#259000
0)
1+
1:
06
14
0;
19
05
b1101111 !
b1101111 ,
13
b10110111 #
b10000001 $
1"
#260000
0"
#261000
1)
0*
0.
16
08
0-
15
07
b11011110 !
b11011110 ,
1;
b1101111 #
b10000010 $
1"
#262000
0"
#263000
1*
0+
0:
18
00
1.
09
17
0/
b10111101 !
b10111101 ,
1-
b11011110 #
b10000011 $
1"
#264000
0"
#265000
10
02
1:
1/
01
19
b1111011 !
b1111011 ,
0;
b10111101 #
b10000100 $
1"
#266000
0"
#267000
0)
0*
04
12
1;
03
b11110111 !
b11110111 ,
11
b1111011 #
b10000101 $
1"
#268000
0"
#269000
1)
1+
0.
14
06
0-
13
b11101110 !
b11101110 ,
05
b11110111 #
b10000110 $
1"
#270000
0"
#271000
08
16
00
1.
07
15
0/
b11011101 !
b11011101 ,
1-
b11101110 #
b10000111 $
1"
#272000
0"
#273000
0+
1*
10
02
18
0:
1/
01
17
b10111011 !
b10111011 ,
09
b11011101 #
b10001000 $
1"
#274000
0"
#275000
1:
04
12
0;
19
03
b1110111 !
b1110111 ,
11
b10111011 #
b10001001 $
1"
#276000
0"
#277000
1+
0*
14
06
13
05
b11101111 !
b11101111 ,
1;
b1110111 #
b10001010 $
1"
#278000
0"
#279000
08
16
07
b11011111 !
b11011111 ,
15
b11101111 #
b10001011 $
1"
#280000
0"
#281000
0+
1*
18
0:
17
b10111111 !
b10111111 ,
09
b11011111 #
b10001100 $
1"
#282000
0"
#283000
1:
0;
b1111111 !
b1111111 ,
19
b10111111 #
b10001101 $
1"
#284000
0"
#285000
0)
0*
b11111111 !
b11111111 ,
1;
b1111111 #
b10001110 $
1"
#286000
0"
#287000
0.
b11111110 !
b11111110 ,
0-
b11111111 #
b10001111 $
1"
#288000
0"
#289000
00
b11111100 !
b11111100 ,
0/
b11111110 #
b10010000 $
1"
#290000
0"
#291000
02
b11111000 !
b11111000 ,
01
b11111100 #
b10010001 $
1"
#292000
0"
#293000
04
b11110000 !
b11110000 ,
03
b11111000 #
b10010010 $
1"
#294000
0"
#295000
1)
1+
06
b11100000 !
b11100000 ,
05
b11110000 #
b10010011 $
1"
#296000
0"
#297000
0)
0+
1.
08
1-
b11000001 !
b11000001 ,
07
b11100000 #
b10010100 $
1"
#298000
0"
#299000
1)
1*
0:
10
0.
09
1/
b10000010 !
b10000010 ,
0-
b11000001 #
b10010101 $
1"
#300000
0"
#301000
0)
0*
1.
00
12
1-
0/
11
b101 !
b101 ,
0;
b10000010 #
b10010110 $
1"
#302000
0"
#303000
14
02
10
0.
13
01
1/
b1010 !
b1010 ,
0-
b101 #
b10010111 $
1"
#304000
0"
#305000
1)
1+
00
12
04
16
0/
11
03
b10100 !
b10100 ,
15
b1010 #
b10011000 $
1"
#306000
0"
#307000
18
06
14
02
1.
17
05
13
01
b101001 !
b101001 ,
1-
b10100 #
b10011001 $
1"
#308000
0"
#309000
0)
1*
10
04
16
08
1:
1/
03
15
07
b1010011 !
b1010011 ,
19
b101001 #
b10011010 $
1"
#310000
0"
#311000
0:
18
06
12
0.
1;
09
17
05
11
b10100110 !
b10100110 ,
0-
b1010011 #
b10011011 $
1"
#312000
0"
#313000
1)
0+
00
14
08
1:
0/
13
07
19
b1001100 !
b1001100 ,
0;
b10100110 #
b10011100 $
1"
#314000
0"
#315000
0)
1+
0:
16
02
1.
1;
09
15
01
b10011001 !
b10011001 ,
1-
b1001100 #
b10011101 $
1"
#316000
0"
#317000
0+
0*
0.
10
04
18
0-
1/
03
17
b110010 !
b110010 ,
0;
b10011001 #
b10011110 $
1"
#318000
0"
#319000
1*
1+
1:
06
12
00
19
05
11
b1100100 !
b1100100 ,
0/
b110010 #
b10011111 $
1"
#320000
0"
#321000
0+
0*
02
14
08
01
13
07
b11001000 !
b11001000 ,
1;
b1100100 #
b10100000 $
1"
#322000
0"
#323000
1*
1+
0:
16
04
09
15
b10010000 !
b10010000 ,
03
b11001000 #
b10100001 $
1"
#324000
0"
#325000
1)
0*
06
18
05
17
b100000 !
b100000 ,
0;
b10010000 #
b10100010 $
1"
#326000
0"
#327000
1*
0+
1:
08
1.
19
07
b1000001 !
b1000001 ,
1-
b100000 #
b10100011 $
1"
#328000
0"
#329000
10
0:
1/
09
b10000011 !
b10000011 ,
1;
b1000001 #
b10100100 $
1"
#330000
0"
#331000
0)
0*
12
0;
b111 !
b111 ,
11
b10000011 #
b10100101 $
1"
#332000
0"
#333000
0.
14
0-
b1110 !
b1110 ,
13
b111 #
b10100110 $
1"
#334000
0"
#335000
1)
1+
16
00
15
b11100 !
b11100 ,
0/
b1110 #
b10100111 $
1"
#336000
0"
#337000
0)
0+
1.
02
18
1-
01
b111001 !
b111001 ,
17
b11100 #
b10101000 $
1"
#338000
0"
#339000
1)
1*
1:
04
10
0.
19
03
1/
b1110010 !
b1110010 ,
0-
b111001 #
b10101001 $
1"
#340000
0"
#341000
1+
0*
1.
00
12
06
1-
0/
11
05
b11100101 !
b11100101 ,
1;
b1110010 #
b10101010 $
1"
#342000
0"
#343000
0)
0+
08
14
02
10
07
13
01
b11001011 !
b11001011 ,
1/
b11100101 #
b10101011 $
1"
#344000
0"
#345000
1+
1*
0.
12
04
16
0:
0-
11
03
15
b10010110 !
b10010110 ,
09
b11001011 #
b10101100 $
1"
#346000
0"
#347000
1)
0*
18
06
14
00
0;
17
05
13
b101100 !
b101100 ,
0/
b10010110 #
b10101101 $
1"
#348000
0"
#349000
0)
1*
1.
02
16
08
1:
1-
01
15
07
b1011001 !
b1011001 ,
19
b101100 #
b10101110 $
1"
#350000
0"
#351000
1)
0+
0:
18
04
10
0.
1;
09
17
03
1/
b10110010 !
b10110010 ,
0-
b1011001 #
b10101111 $
1"
#352000
0"
#353000
0)
1+
1.
00
12
06
1:
1-
0/
11
05
19
b1100101 !
b1100101 ,
0;
b10110010 #
b10110000 $
1"
#354000
0"
#355000
0*
0+
08
14
02
10
0.
1;
07
13
01
1/
b11001010 !
b11001010 ,
0-
b1100101 #
b10110001 $
1"
#356000
0"
#357000
1+
1*
00
12
04
16
0:
0/
11
03
15
b10010100 !
b10010100 ,
09
b11001010 #
b10110010 $
1"
#358000
0"
#359000
1)
0*
18
06
14
02
0;
17
05
13
b101000 !
b101000 ,
01
b10010100 #
b10110011 $
1"
#360000
0"
#361000
0)
1*
1.
04
16
08
1:
1-
03
15
07
b1010001 !
b1010001 ,
19
b101000 #
b10110100 $
1"
#362000
0"
#363000
0:
18
06
10
0.
1;
09
17
05
1/
b10100010 !
b10100010 ,
0-
b1010001 #
b10110101 $
1"
#364000
0"
#365000
1)
0+
00
12
08
1:
0/
11
07
19
b1000100 !
b1000100 ,
0;
b10100010 #
b10110110 $
1"
#366000
0"
#367000
0:
14
02
1.
1;
09
13
01
b10001001 !
b10001001 ,
1-
b1000100 #
b10110111 $
1"
#368000
0"
#369000
1+
0*
10
04
16
1/
03
15
b10011 !
b10011 ,
0;
b10001001 #
b10111000 $
1"
#370000
0"
#371000
18
06
12
17
05
b100111 !
b100111 ,
11
b10011 #
b10111001 $
1"
#372000
0"
#373000
0+
1*
14
08
1:
13
07
b1001111 !
b1001111 ,
19
b100111 #
b10111010 $
1"
#374000
0"
#375000
0)
1+
0:
16
1;
09
b10011111 !
b10011111 ,
15
b1001111 #
b10111011 $
1"
#376000
0"
#377000
0+
0*
0.
18
0-
17
b111110 !
b111110 ,
0;
b10011111 #
b10111100 $
1"
#378000
0"
#379000
1)
1*
1:
00
19
b1111100 !
b1111100 ,
0/
b111110 #
b10111101 $
1"
#380000
0"
#381000
0)
0*
1.
02
1-
01
b11111001 !
b11111001 ,
1;
b1111100 #
b10111110 $
1"
#382000
0"
#383000
04
10
0.
03
1/
b11110010 !
b11110010 ,
0-
b11111001 #
b10111111 $
1"
#384000
0"
#385000
1)
1+
00
12
06
0/
11
b11100100 !
b11100100 ,
05
b11110010 #
b11000000 $
1"
#386000
0"
#387000
0)
0+
08
14
02
1.
07
13
01
b11001001 !
b11001001 ,
1-
b11100100 #
b11000001 $
1"
#388000
0"
#389000
1+
1*
0.
10
04
16
0:
0-
1/
03
15
b10010010 !
b10010010 ,
09
b11001001 #
b11000010 $
1"
#390000
0"
#391000
1)
0*
18
06
12
00
0;
17
05
11
b100100 !
b100100 ,
0/
b10010010 #
b11000011 $
1"
#392000
0"
#393000
0+
1*
1.
02
14
08
1:
1-
01
13
07
b1001001 !
b1001001 ,
19
b100100 #
b11000100 $
1"
#394000
0"
#395000
0)
1+
0:
16
04
10
1;
09
15
03
b10010011 !
b10010011 ,
1/
b1001001 #
b11000101 $
1"
#396000
0"
#397000
1)
0*
0.
12
06
18
0-
11
05
17
b100110 !
b100110 ,
0;
b10010011 #
b11000110 $
1"
#398000
0"
#399000
1*
0+
1:
08
14
00
1.
19
07
13
0/
b1001101 !
b1001101 ,
1-
b100110 #
b11000111 $
1"
#400000
0"
#401000
0)
1+
10
02
16
0:
1/
01
15
09
b10011011 !
b10011011 ,
1;
b1001101 #
b11001000 $
1"
#402000
0"
#403000
0*
0+
18
04
12
0.
0;
17
03
11
b110110 !
b110110 ,
0-
b10011011 #
b11001001 $
1"
#404000
0"
#405000
1+
1*
00
14
06
1:
0/
13
05
b1101100 !
b1101100 ,
19
b110110 #
b11001010 $
1"
#406000
0"
#407000
1)
0*
08
16
02
1;
07
15
b11011000 !
b11011000 ,
01
b1101100 #
b11001011 $
1"
#408000
0"
#409000
0+
1*
1.
04
18
0:
1-
03
17
b10110001 !
b10110001 ,
09
b11011000 #
b11001100 $
1"
#410000
0"
#411000
0)
1+
1:
06
10
0;
19
05
b1100011 !
b1100011 ,
1/
b10110001 #
b11001101 $
1"
#412000
0"
#413000
0+
0*
0.
12
08
0-
11
07
b11000110 !
b11000110 ,
1;
b1100011 #
b11001110 $
1"
#414000
0"
#415000
1)
1*
0:
14
00
09
13
b10001100 !
b10001100 ,
0/
b11000110 #
b11001111 $
1"
#416000
0"
