day32/moore_10110_overlapping/design.v
// moore overlapping 10110
module moore(
	input in_seq,clk,rst,
	output reg out);
reg [2:0]ps,ns;
parameter idle = 3'b000;
parameter s1 = 3'b001;
parameter s10 = 3'b010;
parameter s101 = 3'b011;
parameter s1011 = 3'b100;
parameter s10110 = 3'b101;

always@(posedge clk)
	begin
	if(!rst)
		ps<=idle;
	else 
		ps<=ns;
	end

always@(in_seq,ps)begin
case(ps)
	idle: if(in_seq)begin
		ns=s1;
		out=0;
		end
		else begin
		ns=idle;
		out=0;
		end
		
	s1: if(in_seq)begin
		ns=s1;
		out=0;
		end
		else begin
		ns=s10;
		out=0;
		end
	s10: if(in_seq)begin
		ns=s101;
		out=0;
		end
		else begin
		ns=idle;
		out=0;
		end
	s101: if(in_seq)begin
		ns=s1011;
		out=0;
		end
		else begin
		ns=s1;
		out=0;
		end
	s1011: if(in_seq)begin
		ns=s1;
		out=0;
		end
		else begin
		ns=s10110;
		out=0;
		end
	s10110: if(in_seq)begin
		ns=s101;
		out=1;
		end
		else begin
		ns=idle;
		out=1;
		end
	endcase
	end
endmodule

day32/moore_10110_overlapping/testbench.v
`include"design.v"
// test bench
module tb;
reg in_seq,clk,rst;
wire out;
moore dut(.*);
initial begin
$monitor("time = %0t in_sequence = %b out = %b",$time,in_seq,out);
clk=0;
rst=0;
#12 rst=1;
in_seq=1;
#10 in_seq=0;
#10 in_seq=1;
#10 in_seq=1;
#10 in_seq=0;
#10 in_seq=1;
#10 in_seq=0;
#10 in_seq=1;
#10 in_seq=1;
#10 in_seq=0;

#20 $finish;
end
always #5 clk =~clk;
initial begin 
$dumpfile("dump.vcd");
$dumpvars(0,tb);
end
endmodule

day32/moore_10110_overlapping/dump.vcd
$date
	Wed May 14 10:04:05 2025
$end
$version
	Icarus Verilog
$end
$timescale
	1s
$end
$scope module tb $end
$var wire 1 ! out $end
$var reg 1 " clk $end
$var reg 1 # in_seq $end
$var reg 1 $ rst $end
$scope module dut $end
$var wire 1 " clk $end
$var wire 1 # in_seq $end
$var wire 1 $ rst $end
$var parameter 3 % idle $end
$var parameter 3 & s1 $end
$var parameter 3 ' s10 $end
$var parameter 3 ( s101 $end
$var parameter 3 ) s1011 $end
$var parameter 3 * s10110 $end
$var reg 3 + ns [2:0] $end
$var reg 1 ! out $end
$var reg 3 , ps [2:0] $end
$upscope $end
$upscope $end
$enddefinitions $end
$comment Show the parameter values. $end
$dumpall
b101 *
b100 )
b11 (
b10 '
b1 &
b0 %
$end
#0
$dumpvars
bx ,
bx +
0$
x#
0"
x!
$end
#5
0!
b0 +
b0 ,
1"
#10
0"
#12
b1 +
1#
1$
#15
b1 ,
1"
#20
0"
#22
b10 +
0#
#25
b0 +
b10 ,
1"
#30
0"
#32
b11 +
1#
#35
b100 +
b11 ,
1"
#40
0"
#45
b1 +
b100 ,
1"
#50
0"
#52
b101 +
0#
#55
1!
b0 +
b101 ,
1"
#60
0"
#62
b11 +
1#
#65
0!
b100 +
b11 ,
1"
#70
0"
#72
b1 +
0#
#75
b10 +
b1 ,
1"
#80
0"
#82
b1 +
1#
#85
1"
#90
0"
#95
1"
#100
0"
#102
b10 +
0#
#105
b0 +
b10 ,
1"
#110
0"
#115
b0 ,
1"
