day16/tlatch/latch.v
// design code for d latch
module tlatch(
	input t,clk,rst,
	output reg q);
	reg temp;
always@(t,clk,rst)begin
	if(~clk)
		if(rst)
		temp<=0;
		else if(t)
		temp<=~temp;
	else 
	temp<=temp;
q=temp;
end
endmodule



// test bench

module tb;
reg t,clk,rst;
output q;
tlatch dut(t,clk,rst,q);

initial begin
$monitor("t = %b  clk = %b  reset =%b  ::  output q = %b ",t,clk,rst,q);
for(integer i =0; i<2**3;i++)begin
{t,rst,clk}=i; #5; end
end

initial begin
$dumpfile("dump.vcd");
$dumpvars(0,tb);
end
endmodule

day16/tlatch/dump.vcd
$date
	Tue Apr 22 17:17:09 2025
$end
$version
	Icarus Verilog
$end
$timescale
	1s
$end
$scope module tb $end
$var wire 1 ! q $end
$var reg 1 " clk $end
$var reg 1 # rst $end
$var reg 1 $ t $end
$scope module dut $end
$var wire 1 " clk $end
$var wire 1 # rst $end
$var wire 1 $ t $end
$var reg 1 ! q $end
$var reg 1 % temp $end
$upscope $end
$scope begin $ivl_for_loop0 $end
$var integer 32 & i [31:0] $end
$upscope $end
$upscope $end
$enddefinitions $end
$comment Show the parameter values. $end
$dumpall
$end
#0
$dumpvars
b0 &
x%
0$
0#
0"
x!
$end
#5
1"
b1 &
#10
0%
1#
0"
b10 &
#15
0!
1"
b11 &
#20
1%
1$
0#
0"
b100 &
#25
1!
1"
b101 &
#30
0%
1#
0"
b110 &
#35
0!
1"
b111 &
#40
b1000 &
