day16/tlatch/latch.v
// design code for d latch
module tlatch(
	input t,clk,rst,
	output reg q);
	reg temp;
always@(t,clk,rst)begin
	if(!clk)
		if(rst)
		temp=0;
		else if(t)
		temp=~temp;
q=temp;
end
endmodule



// test bench

module tb;
reg t,clk,rst;
output q;
tlatch dut(t,clk,rst,q);

initial begin
$monitor("t = %b  clk = %b  reset =%b  ::  output q = %b ",t,clk,rst,q);
begin
 rst=1; t=0; clk=0;
#5 rst =0;
end
for(integer i =0; i<2**5;i++)begin
{t,clk}=i; #5; end
end

initial begin
$dumpfile("dump.vcd");
$dumpvars(0,tb);
end
endmodule

day16/tlatch/dump.vcd
$date
	Wed Apr 23 12:56:56 2025
$end
$version
	Icarus Verilog
$end
$timescale
	1s
$end
$scope module tb $end
$var wire 1 ! q $end
$var reg 1 " clk $end
$var reg 1 # rst $end
$var reg 1 $ t $end
$scope module dut $end
$var wire 1 " clk $end
$var wire 1 # rst $end
$var wire 1 $ t $end
$var reg 1 ! q $end
$var reg 1 % temp $end
$upscope $end
$scope begin $ivl_for_loop0 $end
$var integer 32 & i [31:0] $end
$upscope $end
$upscope $end
$enddefinitions $end
$comment Show the parameter values. $end
$dumpall
$end
#0
$dumpvars
bx &
0%
0$
1#
0"
0!
$end
#5
b0 &
0#
#10
1"
b1 &
#15
1!
1%
1$
0"
b10 &
#20
1"
b11 &
#25
0$
0"
b100 &
#30
1"
b101 &
#35
0!
0%
1$
0"
b110 &
#40
1"
b111 &
#45
0$
0"
b1000 &
#50
1"
b1001 &
#55
1!
1%
1$
0"
b1010 &
#60
1"
b1011 &
#65
0$
0"
b1100 &
#70
1"
b1101 &
#75
0!
0%
1$
0"
b1110 &
#80
1"
b1111 &
#85
0$
0"
b10000 &
#90
1"
b10001 &
#95
1!
1%
1$
0"
b10010 &
#100
1"
b10011 &
#105
0$
0"
b10100 &
#110
1"
b10101 &
#115
0!
0%
1$
0"
b10110 &
#120
1"
b10111 &
#125
0$
0"
b11000 &
#130
1"
b11001 &
#135
1!
1%
1$
0"
b11010 &
#140
1"
b11011 &
#145
0$
0"
b11100 &
#150
1"
b11101 &
#155
0!
0%
1$
0"
b11110 &
#160
1"
b11111 &
#165
b100000 &
