day16/dlatch_s/dlatch.v
// design code for d latch
module dlatch(
	input d,clk,rst,
	output reg q);
always@(d,clk,rst)begin
	if(clk)
		if(rst)
		q<=1'b0;
		else
		q<=d;
	else
	q<=q;
end
endmodule



// test bench

module tb;
reg d,clk,rst;
output q;
dlatch dut(d,clk,rst,q);

initial begin
$monitor("d = %b  clk = %b  reset =%b  ::  output q = %b ",d,clk,rst,q);
for(integer i =0; i<2**3;i++)begin
{clk,rst,d}=i; #5; end
end

initial begin
$dumpfile("dump.vcd");
$dumpvars(0,tb);
end
endmodule

day16/dlatch_s/dump.vcd
$date
	Tue Apr 22 16:49:03 2025
$end
$version
	Icarus Verilog
$end
$timescale
	1s
$end
$scope module tb $end
$var wire 1 ! q $end
$var reg 1 " clk $end
$var reg 1 # d $end
$var reg 1 $ rst $end
$scope module dut $end
$var wire 1 " clk $end
$var wire 1 # d $end
$var wire 1 $ rst $end
$var reg 1 ! q $end
$upscope $end
$scope begin $ivl_for_loop0 $end
$var integer 32 % i [31:0] $end
$upscope $end
$upscope $end
$enddefinitions $end
$comment Show the parameter values. $end
$dumpall
$end
#0
$dumpvars
b0 %
0$
0#
0"
x!
$end
#5
1#
b1 %
#10
1$
0#
b10 %
#15
1#
b11 %
#20
0!
1"
0$
0#
b100 %
#25
1!
1#
b101 %
#30
0!
1$
0#
b110 %
#35
1#
b111 %
#40
b1000 %
