day44/pipeline/testbench.v
module instruction_memory(input [3:0] pc, output reg [7:0] instruction);
reg [7:0] mem[0:15];
initial begin
    mem[0] = 8'b00010001;
    mem[1] = 8'b00010010;
    mem[2] = 8'b00010100;
    mem[3] = 8'b00011001;
    mem[4] = 8'b00000000;
end
always @(*) begin
    instruction = mem[pc];
end
endmodule


module register_file(
    input clk,
    input write_enable,
    input [1:0] read_reg1, read_reg2, write_reg,
    input [7:0] write_data,
    output reg [7:0] read_data1, read_data2
);
reg [7:0] regs[0:3];
always @(posedge clk) begin
    if (write_enable)
        regs[write_reg] <= write_data;
end
always @(*) begin
    read_data1 = regs[read_reg1];
    read_data2 = regs[read_reg2];
end
endmodule


module alu(
    input [7:0] a, b,
    input [3:0] opcode,
    output reg [7:0] result
);
always @(*) begin
    case(opcode)
        4'b0001: result = a + b;
        4'b0010: result = a - b;
        default: result = 8'b0;
    endcase
end
endmodule


module pipeline_top(input clk, input rst);
reg [3:0] pc;
wire [7:0] instr;
reg [7:0] IF_ID, ID_EX_A, ID_EX_B;
reg [3:0] ID_EX_opcode;
reg [1:0] ID_EX_dest;
reg [7:0] EX_MEM_result;
reg [1:0] EX_MEM_dest;
reg MEM_WB_write_en;
reg [7:0] MEM_WB_data;
reg [1:0] MEM_WB_dest;
wire [7:0] reg_data1, reg_data2;
wire [7:0] alu_result;

instruction_memory imem(pc, instr);
register_file rf(
    .clk(clk),
    .write_enable(MEM_WB_write_en),
    .read_reg1(IF_ID[3:2]),
    .read_reg2(IF_ID[1:0]),
    .write_reg(MEM_WB_dest),
    .write_data(MEM_WB_data),
    .read_data1(reg_data1),
    .read_data2(reg_data2)
);
alu my_alu(
    .a(ID_EX_A),
    .b(ID_EX_B),
    .opcode(ID_EX_opcode),
    .result(alu_result)
);

always @(posedge clk or posedge rst) begin
    if (rst) begin
        pc <= 0;
        IF_ID <= 0;
        ID_EX_A <= 0;
        ID_EX_B <= 0;
        ID_EX_opcode <= 0;
        ID_EX_dest <= 0;
        EX_MEM_result <= 0;
        EX_MEM_dest <= 0;
        MEM_WB_data <= 0;
        MEM_WB_dest <= 0;
        MEM_WB_write_en <= 0;
    end else begin
        pc <= pc + 1;
        IF_ID <= instr;
        ID_EX_opcode <= IF_ID[7:4];
        ID_EX_A <= reg_data1;
        ID_EX_B <= reg_data2;
        ID_EX_dest <= IF_ID[1:0];
        EX_MEM_result <= alu_result;
        EX_MEM_dest <= ID_EX_dest;
        MEM_WB_data <= EX_MEM_result;
        MEM_WB_dest <= EX_MEM_dest;
        MEM_WB_write_en <= 1;
    end
end
endmodule


`timescale 1ns / 1ps

module tb;

reg clk;
reg rst;

pipeline_top uut (
    .clk(clk),
    .rst(rst)
);

always #5 clk = ~clk;

initial begin
    $dumpfile("dump.vcd");
    $dumpvars(0, tb);
    clk = 0;
    rst = 1;
    #10;
    rst = 0;
    #150;
    $finish;
end

endmodule

day44/pipeline/dump.vcd
$date
	Fri Jun 20 16:08:24 2025
$end
$version
	Icarus Verilog
$end
$timescale
	1ps
$end
$scope module tb $end
$var reg 1 ! clk $end
$var reg 1 " rst $end
$scope module uut $end
$var wire 1 ! clk $end
$var wire 1 " rst $end
$var wire 8 # reg_data2 [7:0] $end
$var wire 8 $ reg_data1 [7:0] $end
$var wire 8 % instr [7:0] $end
$var wire 8 & alu_result [7:0] $end
$var reg 2 ' EX_MEM_dest [1:0] $end
$var reg 8 ( EX_MEM_result [7:0] $end
$var reg 8 ) ID_EX_A [7:0] $end
$var reg 8 * ID_EX_B [7:0] $end
$var reg 2 + ID_EX_dest [1:0] $end
$var reg 4 , ID_EX_opcode [3:0] $end
$var reg 8 - IF_ID [7:0] $end
$var reg 8 . MEM_WB_data [7:0] $end
$var reg 2 / MEM_WB_dest [1:0] $end
$var reg 1 0 MEM_WB_write_en $end
$var reg 4 1 pc [3:0] $end
$scope module imem $end
$var wire 4 2 pc [3:0] $end
$var reg 8 3 instruction [7:0] $end
$upscope $end
$scope module my_alu $end
$var wire 8 4 a [7:0] $end
$var wire 8 5 b [7:0] $end
$var wire 4 6 opcode [3:0] $end
$var reg 8 7 result [7:0] $end
$upscope $end
$scope module rf $end
$var wire 1 ! clk $end
$var wire 2 8 read_reg1 [1:0] $end
$var wire 2 9 read_reg2 [1:0] $end
$var wire 8 : write_data [7:0] $end
$var wire 1 0 write_enable $end
$var wire 2 ; write_reg [1:0] $end
$var reg 8 < read_data1 [7:0] $end
$var reg 8 = read_data2 [7:0] $end
$upscope $end
$upscope $end
$upscope $end
$enddefinitions $end
$comment Show the parameter values. $end
$dumpall
$end
#0
$dumpvars
bx =
bx <
b0 ;
b0 :
b0 9
b0 8
b0 7
b0 6
b0 5
b0 4
b10001 3
b0 2
b0 1
00
b0 /
b0 .
b0 -
b0 ,
b0 +
b0 *
b0 )
b0 (
b0 '
b0 &
b10001 %
bx $
bx #
1"
0!
$end
#5000
1!
#10000
0!
0"
#15000
b1 9
b10010 %
b10010 3
10
bx *
bx 5
bx )
bx 4
b10001 -
b1 1
b1 2
1!
#20000
0!
#25000
b0 $
b0 <
bx &
bx 7
b10 9
b10100 %
b10100 3
b1 +
b1 ,
b1 6
b10010 -
b10 1
b10 2
1!
#30000
0!
#35000
b0 #
b0 =
bx $
bx <
b1 8
b0 9
b11001 %
b11001 3
b1 '
bx (
b10 +
b0 )
b0 4
b10100 -
b11 1
b11 2
1!
#40000
0!
#45000
bx #
bx =
b10 8
b1 9
b0 %
b0 3
b1 /
b1 ;
bx .
bx :
b10 '
b0 +
b0 *
b0 5
bx )
bx 4
b11001 -
b100 1
b100 2
1!
#50000
0!
#55000
b0 #
b0 =
b0 $
b0 <
b0 8
b0 9
bx %
bx 3
b10 /
b10 ;
b0 '
b1 +
bx *
bx 5
b0 -
b101 1
b101 2
1!
#60000
0!
#65000
bx #
bx =
bx $
bx <
b0 &
b0 7
bx 8
bx 9
b0 /
b0 ;
b1 '
b0 +
b0 *
b0 5
b0 )
b0 4
b0 ,
b0 6
bx -
b110 1
b110 2
1!
#70000
0!
#75000
b1 /
b1 ;
b0 '
b0 (
bx +
bx *
bx 5
bx )
bx 4
bx ,
bx 6
b111 1
b111 2
1!
#80000
0!
#85000
b0 /
b0 ;
b0 .
b0 :
bx '
b1000 1
b1000 2
1!
#90000
0!
#95000
bx /
bx ;
b1001 1
b1001 2
1!
#100000
0!
#105000
b1010 1
b1010 2
1!
#110000
0!
#115000
b1011 1
b1011 2
1!
#120000
0!
#125000
b1100 1
b1100 2
1!
#130000
0!
#135000
b1101 1
b1101 2
1!
#140000
0!
#145000
b1110 1
b1110 2
1!
#150000
0!
#155000
b1111 1
b1111 2
1!
