day15/behavioral_fa/fa.v
// full adder using behavioral statement
module fa(
	input a,b,cin,
	output reg sum,carry);
reg p;
always@(a or b or cin)begin
	p=a^b;
	sum=p^cin;
	carry=(a&b)|(p&cin);
	end
endmodule

// test bench 

module tb;
reg a,b,cin;
wire sum,carry;
fa dut(a,b,cin,sum,carry);
initial begin
$monitor("a =%b b=%b c=%b :: sum=%b carry =%b",a,b,cin,sum,carry);
for(integer i=0;i<2**3;i=i+1)begin
{a,b,cin}=i; #5; end
end
initial begin 
$dumpfile("dump.vcd");
$dumpvars(0,tb);
end
endmodule

day15/behavioral_fa/dump.vcd
$date
	Mon Apr 21 17:20:58 2025
$end
$version
	Icarus Verilog
$end
$timescale
	1s
$end
$scope module tb $end
$var wire 1 ! sum $end
$var wire 1 " carry $end
$var reg 1 # a $end
$var reg 1 $ b $end
$var reg 1 % cin $end
$scope module dut $end
$var wire 1 # a $end
$var wire 1 $ b $end
$var wire 1 % cin $end
$var reg 1 " carry $end
$var reg 1 & p $end
$var reg 1 ! sum $end
$upscope $end
$scope begin $ivl_for_loop0 $end
$var integer 32 ' i [31:0] $end
$upscope $end
$upscope $end
$enddefinitions $end
$comment Show the parameter values. $end
$dumpall
$end
#0
$dumpvars
b0 '
0&
0%
0$
0#
0"
0!
$end
#5
1!
1%
b1 '
#10
1&
1$
0%
b10 '
#15
1"
0!
1%
b11 '
#20
0"
1!
1#
0$
0%
b100 '
#25
1"
0!
1%
b101 '
#30
0&
1$
0%
b110 '
#35
1!
1%
b111 '
#40
b1000 '
